py_todo_csv/.list.csv
py_todo_csv/__init__.py
py_todo_csv/main.py
py_todo_csv-0.1.0.dist-info/METADATA
py_todo_csv-0.1.0.dist-info/WHEEL
py_todo_csv-0.1.0.dist-info/entry_points.txt
py_todo_csv-0.1.0.dist-info/RECORD
